docker_plugin_api/IpamDriverEntities.py
docker_plugin_api/NetworkDriverEntities.py
docker_plugin_api/Plugin.py
docker_plugin_api/__init__.py
docker_plugin_api-0.3.dist-info/LICENSE
docker_plugin_api-0.3.dist-info/METADATA
docker_plugin_api-0.3.dist-info/WHEEL
docker_plugin_api-0.3.dist-info/top_level.txt
docker_plugin_api-0.3.dist-info/RECORD
