Metadata-Version: 2.1
Name: docker-plugin-api
Version: 0.3
Summary: Python interface to Docker Plugin API
Home-page: https://github.com/jacekkow/docker-plugin-api
Author: Jacek Kowalski
Author-email: Jacek@jacekk.info
License: BSD
Platform: UNKNOWN
Classifier: Intended Audience :: Developers
Classifier: License :: OSI Approved :: BSD License
Classifier: Operating System :: OS Independent
Classifier: Programming Language :: Python :: 3 :: Only
Requires-Python: >=3.6
Requires-Dist: Flask
